README.rst
setup.py
b2tool/__init__.py
b2tool/conf.py
b2tool/main.py
b2tool/rules.py
b2tool.egg-info/PKG-INFO
b2tool.egg-info/SOURCES.txt
b2tool.egg-info/dependency_links.txt
b2tool.egg-info/entry_points.txt
b2tool.egg-info/requires.txt
b2tool.egg-info/top_level.txt
b2tool/commands/__init__.py
b2tool/commands/auth.py
b2tool/commands/pull_request.py