Metadata-Version: 1.1
Name: b2tool
Version: 0.0.4
Summary: bbtool is a command line tool to manage BitBucket
Home-page: https://github.com/jesuejunior/b2tool
Author: Jesue Junior
Author-email: talkto@jesuejunior.com
License: 3-BSD
Platform: UNKNOWN
Classifier: License :: OSI Approved :: BSD License
Classifier: Operating System :: OS Independent
Classifier: Programming Language :: Python
Classifier: Topic :: Software Development :: Libraries :: Application Frameworks
